{"cameraMode":{"drawMode":0,"name":"Shaded","section":"Shading Mode"},"sceneLighting":false,"audioPlay":false,"sceneViewState":{"showFog":true,"showMaterialUpdate":false,"showSkybox":false,"showFlares":true,"showImageEffects":true,"showParticleSystems":true},"in2DMode":false,"pivot":{"x":-12.09046745300293,"y":12.294299125671387,"z":25.180696487426759},"rotation":{"x":0.029177114367485048,"y":0.6207419037818909,"z":-0.023067589849233629,"w":0.7831864356994629},"size":1.1137933731079102,"orthographic":false}